{"spatialClusterName": "Leipzig", "creator": "Senftlebius, Andreas", "spatialRaw": "Lipsiae", "title": "Andreae Senftlebi[i] Nuces Saturnalitiae", "publisher": "Lischkius  Staatsbibliothek zu Berlin \u2013 Preu\u00dfischer Kulturbesitz, Germany", "mediatype": "Monograph", "spatialClean": "Lipsiae", "source": "Senftlebius, Andreas: Andreae Senftlebi[i] Nuces Saturnalitiae  Ad Virum Ampli\u00dfimum, Clari\u00dfimum, Bernhardum Guilielmum N\u00fcslerum .... Lipsiae  Berlin", "dateClean": "1738", "lat": "51.3391827", "alternative": "Ad Virum Ampli\u00dfimum, Clari\u00dfimum, Bernhardum Guilielmum N\u00fcslerum ...", "lng": "12.3810549", "subject": "Historische Drucke"}