{"ppn": "PPN630945543", "dateClean": "1749", "title": "Edict, Da\u00df diejenigen, Welche In dem Hertzogthum Schlesien, Und der Graffschaft Glatz, Sich den Studiis wiedmen, auf einheimischen Schulen und Universit\u00e4ten studiren, Wiedrigenfalls In Sr. K\u00f6nigl. Majest\u00e4t Landen keine Bef\u00f6rderung hoffen sollen", "creator": "nan", "spatialClusterName": "Breslau", "spatialClean": "Bre\u00dflau", "spatialRaw": "Bre\u00dflau", "mediatype": "Monograph", "subject": "Historische Drucke", "source": "Edict, Da\u00df diejenigen, Welche In dem Hertzogthum Schlesien, Und der Graffschaft Glatz, Sich den Studiis wiedmen, auf einheimischen Schulen und Universit\u00e4ten studiren, Wiedrigenfalls In Sr. K\u00f6nigl. Majest\u00e4t Landen keine Bef\u00f6rderung hoffen sollen  [Gegeben Berlin den 25sten Decembris Anno 1749.]. Bre\u00dflau 1749", "publisher": "Gra\u00df", "alternative": "[Gegeben Berlin den 25sten Decembris Anno 1749.]", "lat": "51.1089776", "lng": "17.0326689", "textCluster": "9", "creatorCluster": "0"}