{"ppn": "PPN68768983X", "dateClean": "1591", "title": "AUDOMARI || TALAEI RHE-||TORICA || E || P. RAMI REGII PRO-||FESSORIS PRAELECTIO-||NIBUS OBSERVATA.||", "creator": "Talon, Omer  Ramus, Petrus", "spatialClusterName": "Frankfurt", "spatialClean": "Frankfurt/Main", "spatialRaw": "Frankfurt/Main", "mediatype": "Monograph", "subject": "Historische Drucke", "source": "Talon, Omer  Ramus, Petrus: AUDOMARI || TALAEI RHE-||TORICA || E || P. RAMI REGII PRO-||FESSORIS PRAELECTIO-||NIBUS OBSERVATA.||. Frankfurt/Main  Berlin 1591", "publisher": "Aalborg, Hans  Wechel, Johann", "alternative": "nan", "lat": "50.110653", "lng": "8.682093", "textCluster": "9", "creatorCluster": "6"}