{"ppn": "PPN667704477", "dateClean": "1689", "title": "Cupressus Feralis Tumulo Viri Iuvenis Nobilissimi Nobilissimi & Clarissimi Dn. Alberti Hagemeistern, Iuris Utr. Candidati, Solidae eruditionis laude Commendatissimi, spectata vitae integritate & morum humanitate Praecellentissimi, magno inclytae familiae suae desiderio, expletis annis sex & viginti, die 8. Decembr. M.DC.LXXXIX. rebus humanis exempti, Cum non absq[ue] insigni bonorum omnium luctu tumulo inferretur Domin. III. Advent. Sparsa a Fautoribus Et Amicis", "creator": "nan", "spatialClusterName": "Stralsund", "spatialClean": "Stralsundi", "spatialRaw": "Stralsundi", "mediatype": "Monograph", "subject": "Historische Drucke", "source": "Cupressus Feralis Tumulo Viri Iuvenis Nobilissimi Nobilissimi & Clarissimi Dn. Alberti Hagemeistern, Iuris Utr. Candidati, Solidae eruditionis laude Commendatissimi, spectata vitae integritate & morum humanitate Praecellentissimi, magno inclytae familiae suae desiderio, expletis annis sex & viginti, die 8. Decembr. M.DC.LXXXIX. rebus humanis exempti, Cum non absq[ue] insigni bonorum omnium luctu tumulo inferretur Domin. III. Advent. Sparsa a Fautoribus Et Amicis. Stralsundi  Berlin 1689", "publisher": "Typis Ebelingianis", "alternative": "nan", "lat": "54.3159851", "lng": "13.0904622", "textCluster": "9", "creatorCluster": "0"}