{"ppn": "PPN645952605", "dateClean": "1802", "title": "Taxe, zu welchen Preisen das Bau-, Nutz- und Brennholz in den Magdeburgschen Forsten verkauft werden soll", "creator": "nan", "spatialClusterName": "Berlin", "spatialClean": "Berlin", "spatialRaw": "Berlin", "mediatype": "Monograph", "subject": "Historische Drucke", "source": "Taxe, zu welchen Preisen das Bau-, Nutz- und Brennholz in den Magdeburgschen Forsten verkauft werden soll  De Dato Berlin, den 23. May 1802. Berlin  Berlin 1802", "publisher": "Decker", "alternative": "De Dato Berlin, den 23. May 1802", "lat": "52.5170365", "lng": "13.3888599", "textCluster": "1690", "creatorCluster": "0"}