{"ppn": "PPN689608462", "dateClean": "1738", "title": "Brief an Joseph Joachim", "creator": "Mendelssohn, Franz von  Joachim, Joseph", "spatialClusterName": "Berlin", "spatialClean": "Berlin", "spatialRaw": "Berlin", "mediatype": "Text", "subject": "Musik", "source": "Mendelssohn, Franz von  Joachim, Joseph: Brief an Joseph Joachim  10.11.1887. Berlin  Berlin", "publisher": "nan", "alternative": "10.11.1887", "lat": "52.5170365", "lng": "13.3888599", "textCluster": "205", "creatorCluster": "897"}