{"ppn": "PPN699915732", "dateClean": "1738", "title": "Unsere Toten", "creator": "Risch, Adolf", "spatialClusterName": "Kaiserslautern", "spatialClean": "Kaiserslautern", "spatialRaw": "Kaiserslautern", "mediatype": "Monograph", "subject": "Krieg 1914 1918", "source": "Risch, Adolf: Unsere Toten  ein Trostwort in Kriegstrauer. Kaiserslautern  Berlin", "publisher": "Verlag des Ev. Vereins Kaiserslautern", "alternative": "ein Trostwort in Kriegstrauer", "lat": "49.4432174", "lng": "7.7689951", "textCluster": "2670", "creatorCluster": "3572"}