{"ppn": "PPN683358227", "dateClean": "1890", "title": "Allgemeines Berggesetz f\u00fcr die Preussischen Staaten vom 24. Juni 1865 in seinem derzeitigen Rechtsstande", "creator": "nan", "spatialClusterName": "Paderborn", "spatialClean": "Paderborn", "spatialRaw": "Paderborn", "mediatype": "Monograph", "subject": "Rechtswissenschaft", "source": "Allgemeines Berggesetz f\u00fcr die Preussischen Staaten vom 24. Juni 1865 in seinem derzeitigen Rechtsstande  Gesetzestext nebst Anmerkungen, den darauf bez\u00fcglichen Gesetzen, Verordnungen, Einf\u00fchrungsbestimmungen f\u00fcr die neu erworbenen Landestheile, sowie die F\u00fcrstenth\u00fcmer Waldeck und Pyrmont, dem Reichsgesetz vom 9. Juni 1884 ... ; zum praktischen Gebrauch f\u00fcr Bergbeamte, Juristen, Bergwerksbesitzer und Bergleute. Paderborn  Berlin 1890", "publisher": "Sch\u00f6ningh", "alternative": "Gesetzestext nebst Anmerkungen, den darauf bez\u00fcglichen Gesetzen, Verordnungen, Einf\u00fchrungsbestimmungen f\u00fcr die neu erworbenen Landestheile, sowie die F\u00fcrstenth\u00fcmer Waldeck und Pyrmont, dem Reichsgesetz vom 9. Juni 1884 ... ; zum praktischen Gebrauch f\u00fcr Bergbeamte, Juristen, Bergwerksbesitzer und Bergleute", "lat": "51.71895955", "lng": "8.76486977817756", "textCluster": "697", "creatorCluster": "0"}