{"spatialClusterName": "K\u00f6nigsberg", "creator": "Dach, Simon", "spatialRaw": "[K\u00f6nigsberg]", "title": "Bey seligem Ableiben Des Weiland Edlen/ Ehrenvesten/ Nahmhafften und Wolweisen Herrn Reinhold von Eggert etc. Der Churf\u00fcrstl. Stadt Kneiphoff K\u00f6nigsberg wolverdienten B\u00fcrgermeisters auff begehren geschrieben", "publisher": "Reusner", "mediatype": "Monograph", "spatialClean": "K\u00f6nigsberg", "source": "Dach, Simon: Bey seligem Ableiben Des Weiland Edlen/ Ehrenvesten/ Nahmhafften und Wolweisen Herrn Reinhold von Eggert etc. Der Churf\u00fcrstl. Stadt Kneiphoff K\u00f6nigsberg wolverdienten B\u00fcrgermeisters auff begehren geschrieben. [K\u00f6nigsberg]  Berlin 1640", "dateClean": "1640", "lat": "54.7066422", "alternative": "nan", "lng": "20.5105166", "subject": "Historische Drucke"}