{"spatialClusterName": "Arnsberg", "creator": "nan", "spatialRaw": "Arnsberg", "title": "Sammlung von Verordnungen, Gesch\u00e4fts-Instruktionen und sonstigen generellen Verf\u00fcgungen", "publisher": "Curt", "mediatype": "Multivolume work", "spatialClean": "Arnsberg", "source": "Sammlung von Verordnungen, Gesch\u00e4fts-Instruktionen und sonstigen generellen Verf\u00fcgungen. Arnsberg  Berlin 1839", "dateClean": "1839", "lat": "51.4002384", "alternative": "nan", "lng": "8.0605908", "subject": "Rechtswissenschaft"}