{"spatialClusterName": "Paris", "creator": "Blahetka, L\u00e9opoldine", "spatialRaw": "Paris", "title": "Pater Noster", "publisher": "Lemoine", "mediatype": "Monograph", "spatialClean": "Paris", "source": "Blahetka, L\u00e9opoldine: Pater Noster  Pour 1er Et 2d Dessus, T\u00e9nor Et Basse Avec Accompt. de Piano Ou Orgue ; Op: 58.. Paris 1835", "dateClean": "1835", "lat": "48.8566101", "alternative": "Pour 1er Et 2d Dessus, T\u00e9nor Et Basse Avec Accompt. de Piano Ou Orgue ; Op: 58.", "lng": "2.3514992", "subject": "Musiknoten"}