{"ppn": "PPN683971433", "dateClean": "1682", "title": "Dissertatio Iuridica De Edaci Locustarum Pernicie", "creator": "Hoppe, Joachim", "spatialClusterName": "Frankfurt", "spatialClean": "Francofurti", "spatialRaw": "Francofurti ad Viadrum", "mediatype": "Other", "subject": "Historische Drucke", "source": "Hoppe, Joachim: Dissertatio Iuridica De Edaci Locustarum Pernicie  Ad L. Excepto tempore 18. C. de Locat. & Conduct.. Francofurti ad Viadrum 1682", "publisher": "Coepselius", "alternative": "Ad L. Excepto tempore 18. C. de Locat. & Conduct.", "lat": "50.110653", "lng": "8.682093", "textCluster": "4538", "creatorCluster": "1003"}