{"spatialClusterName": "Breslau", "creator": "Kremser, ...", "spatialRaw": "Breslau", "title": "Kremser's Geb\u00fchren-Tabellen nach der Geb.-Ordn. f\u00fcr Notare u. dem Preuss. Gerichtskosten-Gesetze vom 25. Juni 1895 in der Fassung von 6. October 1899", "publisher": "Kornicker", "mediatype": "Monograph", "spatialClean": "Breslau", "source": "Kremser, ...: Kremser's Geb\u00fchren-Tabellen nach der Geb.-Ordn. f\u00fcr Notare u. dem Preuss. Gerichtskosten-Gesetze vom 25. Juni 1895 in der Fassung von 6. October 1899. Breslau  Berlin 1899", "dateClean": "1899", "lat": "51.1089776", "alternative": "nan", "lng": "17.0326689", "subject": "Historische Drucke"}