{"ppn": "PPN656574119", "dateClean": "1728", "title": "Des Angenehmen Misch-Masches Artiger, lustiger Und Sinnreicher Historien, ... Continuation", "creator": "Senffleben, Abraham", "spatialClusterName": "None", "spatialClean": "", "spatialRaw": "[S.l.]", "mediatype": "Multivolume work", "subject": "Historische Drucke", "source": "Senffleben, Abraham: Des Angenehmen Misch-Masches Artiger, lustiger Und Sinnreicher Historien, ... Continuation. [S.l.]  Berlin 1728", "publisher": "nan", "alternative": "nan", "lat": "nan", "lng": "nan", "textCluster": "9", "creatorCluster": "4392"}