{"ppn": "PPN688038654", "dateClean": "1743", "title": "La Vedova Ingegnosa", "creator": "Prota, Ignazio  Mariani, Tommaso", "spatialClusterName": "Hamburg", "spatialClean": "Hamburg", "spatialRaw": "[Hamburg]", "mediatype": "Monograph", "subject": "Historische Drucke", "source": "Prota, Ignazio  Mariani, Tommaso: La Vedova Ingegnosa  Intermezzi Per Musica Da Rappresentarsi Nel Teatro Di Citta Amburgo. [Hamburg]  Berlin 1743", "publisher": "Spiering", "alternative": "Intermezzi Per Musica Da Rappresentarsi Nel Teatro Di Citta Amburgo", "lat": "53.550341", "lng": "10.000654", "textCluster": "234", "creatorCluster": "3306"}