{"ppn": "PPN659036541", "dateClean": "1892", "title": "Die Lehrpl\u00e4ne und Pr\u00fcfungsordnungen f\u00fcr die h\u00f6heren Schulen in Preu\u00dfen vom Jahre 1891", "creator": "nan", "spatialClusterName": "Neuwied", "spatialClean": "Neuwied", "spatialRaw": "Neuwied [u.a.]", "mediatype": "Monograph", "subject": "Historische Drucke", "source": "Die Lehrpl\u00e4ne und Pr\u00fcfungsordnungen f\u00fcr die h\u00f6heren Schulen in Preu\u00dfen vom Jahre 1891  mit teils vergleichenden, teils auf die fr\u00fcheren Bestimmungen verweisenden Anmerkungen und eeinem Anhange enthaltend den Normaletat von1892 f\u00fcr die Besoldungen der Leiter und Lehrer der h\u00f6heren Unterrichtsanstalten und die Denkschrift, betreffend die geschichtliche Entwicklung der Revision der Lehrpl\u00e4ne und Pr\u00fcfungsordnungen f\u00fcr h\u00f6here Schulen sowie Gesichtspunkte f\u00fcr die vorgenommenen \u00c4nderungen. Neuwied [u.a.]  Berlin 1892", "publisher": "Heuser", "alternative": "mit teils vergleichenden, teils auf die fr\u00fcheren Bestimmungen verweisenden Anmerkungen und eeinem Anhange enthaltend den Normaletat von1892 f\u00fcr die Besoldungen der Leiter und Lehrer der h\u00f6heren Unterrichtsanstalten und die Denkschrift, betreffend die geschichtliche Entwicklung der Revision der Lehrpl\u00e4ne und Pr\u00fcfungsordnungen f\u00fcr h\u00f6here Schulen sowie Gesichtspunkte f\u00fcr die vorgenommenen \u00c4nderungen", "lat": "50.4302589", "lng": "7.4663112", "textCluster": "9", "creatorCluster": "0"}