{"ppn": "PPN657129305", "dateClean": "1645", "title": "Christliche Leichpredigt Uber den Spruch Job. 19. Ich weis das mein Erl\u00f6ser lebt", "creator": "Thumm, Heinrich", "spatialClusterName": "K\u00f6nigsberg", "spatialClean": "K\u00f6nigsberg", "spatialRaw": "K\u00f6nigsberg", "mediatype": "Monograph", "subject": "Historische Drucke", "source": "Thumm, Heinrich: Christliche Leichpredigt Uber den Spruch Job. 19. Ich weis das mein Erl\u00f6ser lebt  Bey dem Leichbeg\u00e4ngn\u00fc\u00df Des ... Herren Fabians/ De\u00df Heil: R\u00f6mischen Reichs Erbtruchsessen und Freyherrn zu Waldtburg/ K\u00f6nigl. Mayt: zu Pohlen und Schweden ... CammerHerren/ ErbHerren auff Wildenhoff/ Landesberg/ Grosstegen/ Saraunen ... Als er zu Landsberg in sein Erbbegr\u00e4bn\u00fcs Anno 1644. den 20. Iulii beygesetzet worden. Gehalten. K\u00f6nigsberg  Berlin 1645", "publisher": "Reusner", "alternative": "Bey dem Leichbeg\u00e4ngn\u00fc\u00df Des ... Herren Fabians/ De\u00df Heil: R\u00f6mischen Reichs Erbtruchsessen und Freyherrn zu Waldtburg/ K\u00f6nigl. Mayt: zu Pohlen und Schweden ... CammerHerren/ ErbHerren auff Wildenhoff/ Landesberg/ Grosstegen/ Saraunen ... Als er zu Landsberg in sein Erbbegr\u00e4bn\u00fcs Anno 1644. den 20. Iulii beygesetzet worden. Gehalten", "lat": "54.7066422", "lng": "20.5105166", "textCluster": "9", "creatorCluster": "7957"}