{"spatialClusterName": "Torgau", "creator": "Reibold, Hans Christoph  Gersdorff, Hans Abraham", "spatialRaw": "[Torgau]", "title": "Abdanckung/ kurtz Vor angehender Beg\u00e4ngnisz/ auff dem Rathhause zu Torgau/ Von welchem der Procesz ausgangen", "publisher": "[Hempe]", "mediatype": "Other", "spatialClean": "Torgau", "source": "Reibold, Hans Christoph  Gersdorff, Hans Abraham: Abdanckung/ kurtz Vor angehender Beg\u00e4ngnisz/ auff dem Rathhause zu Torgau/ Von welchem der Procesz ausgangen. [Torgau] 1679", "dateClean": "1679", "lat": "51.5581272", "alternative": "nan", "lng": "13.0046538", "subject": "Historische Drucke"}