{"spatialClusterName": "Hamburg", "creator": "Warnicke, ...  Hasse, Johann Adolf  Porpora, Nicol\u00f2  Hurlebusch, Conrad Friedrich  Wend, Christoph Gottlieb", "spatialRaw": "Hamburg", "title": "Hochzeit der Statira, K\u00f6nigin von Persien", "publisher": "Spieringk", "mediatype": "Monograph", "spatialClean": "Hamburg", "source": "Warnicke, ...  Hasse, Johann Adolf  Porpora, Nicol\u00f2  Hurlebusch, Conrad Friedrich  Wend, Christoph Gottlieb: Hochzeit der Statira, K\u00f6nigin von Persien  in einem Singe-Spiele auf dem Hamburgischen Schau-Platze f\u00fcrgestellet. Anno MDCCXXXVII.. Hamburg  Berlin 1737", "dateClean": "1737", "lat": "53.550341", "alternative": "in einem Singe-Spiele auf dem Hamburgischen Schau-Platze f\u00fcrgestellet. Anno MDCCXXXVII.", "lng": "10.000654", "subject": "Historische Drucke"}