{"ppn": "PPN682935883", "dateClean": "1835", "title": "Orthopt\u00e8res Et H\u00e9mipt\u00e8res", "creator": "Audouin, Jean-Victor  Brull\u00e9, Gaspard Auguste", "spatialClusterName": "Paris", "spatialClean": "Paris", "spatialRaw": "Paris  Paris", "mediatype": "Volume", "subject": "Historische Drucke", "source": "Audouin, Jean-Victor  Brull\u00e9, Gaspard Auguste: Orthopt\u00e8res Et H\u00e9mipt\u00e8res. Paris  Paris 1835", "publisher": "Pillot  Moessard", "alternative": "nan", "lat": "48.8566101", "lng": "2.3514992", "textCluster": "9", "creatorCluster": "8224"}