{"spatialClusterName": "Hamburg", "creator": "nan", "spatialRaw": "Hamburg", "title": "Betrachtungen \u00fcber die Antwort des Herrn Hauptpastor Johann Melchior Goezen auf den Extract eines Protokolls des ehrw\u00fcrdigen Ministeriums", "publisher": "nan", "mediatype": "Monograph", "spatialClean": "Hamburg", "source": "Betrachtungen \u00fcber die Antwort des Herrn Hauptpastor Johann Melchior Goezen auf den Extract eines Protokolls des ehrw\u00fcrdigen Ministeriums. Hamburg 1780", "dateClean": "1780", "lat": "53.550341", "alternative": "nan", "lng": "10.000654", "subject": "Historische Drucke"}