{"ppn": "PPN657076813", "dateClean": "1742", "title": "Die Liebe Gottes Und Dero Nutzen", "creator": "Ryhiner, Emanuel", "spatialClusterName": "Basel", "spatialClean": "Basel", "spatialRaw": "[Basel]", "mediatype": "Monograph", "subject": "Historische Drucke", "source": "Ryhiner, Emanuel: Die Liebe Gottes Und Dero Nutzen  Aus Rom. VIII. v. 28. vorgestellt Zu St. Leonhard in Basel, Den 5. Septembris MDCC XLII. Als zur Erden bestattet wurde, Die Viel Ehr- und Tugendreiche Frau Eleonora Elisabetha de Neufville, Des Ehrenvesten, F\u00fcrnehmen und Weisen Herrn Niclaus Iselin, Des Handelsmanns und Beysitzern E.E. Statt-Gerichts der Mehreren Statt. Gewesene Eheliche Hau\u00df-Frau. [Basel]  Berlin 1742", "publisher": "Pistorius", "alternative": "Aus Rom. VIII. v. 28. vorgestellt Zu St. Leonhard in Basel, Den 5. Septembris MDCC XLII. Als zur Erden bestattet wurde, Die Viel Ehr- und Tugendreiche Frau Eleonora Elisabetha de Neufville, Des Ehrenvesten, F\u00fcrnehmen und Weisen Herrn Niclaus Iselin, Des Handelsmanns und Beysitzern E.E. Statt-Gerichts der Mehreren Statt. Gewesene Eheliche Hau\u00df-Frau", "lat": "47.5581077", "lng": "7.5878261", "textCluster": "9", "creatorCluster": "6"}