{"ppn": "PPN659390086", "dateClean": "1674", "title": "Der alte treue Gott", "creator": "Frauendorff, Christoph", "spatialClusterName": "Merseburgi", "spatialClean": "Merseburg", "spatialRaw": "Merseburg", "mediatype": "Monograph", "subject": "Historische Drucke", "source": "Frauendorff, Christoph: Der alte treue Gott  Aus denen Paulinischen Worten. 1. Cor. x. v. 13. Gott ist getreu/ der Euch nicht l\u00e4sset versuchen [et]c. Bey ... Leich-Bestattung. Der ... Reginen/ Des ... Wilhelm Schmieds ... Raths-C\u00e4mmerers ... Hau\u00df-Ehre/ Welche am 4. Martij des 1674. Jahrs ... eingeschlaffen/ und den 8. drauff ... beygesetzet worden. vorgetragen und ... zum Druck gegeben. Merseburg  Berlin 1674", "publisher": "Forberger", "alternative": "Aus denen Paulinischen Worten. 1. Cor. x. v. 13. Gott ist getreu/ der Euch nicht l\u00e4sset versuchen [et]c. Bey ... Leich-Bestattung. Der ... Reginen/ Des ... Wilhelm Schmieds ... Raths-C\u00e4mmerers ... Hau\u00df-Ehre/ Welche am 4. Martij des 1674. Jahrs ... eingeschlaffen/ und den 8. drauff ... beygesetzet worden. vorgetragen und ... zum Druck gegeben", "lat": "nan", "lng": "nan", "textCluster": "1281", "creatorCluster": "1859"}