{"ppn": "PPN644508930", "dateClean": "1759", "title": "Den richtigen Begrif der Liebe der Lehrer gegen die Sch\u00fcler zeiget k\u00fcrzlich, und ladet zugleich Hochgeneigte G\u00f6nner und Freunde unserer Evangelisch-Lutherischen Schule zu der auf den 30ten April 1759. \u00f6ffentlich anzustellenden Pr\u00fcfung der Schuliugend und einer damit verbundenen Red\u00fcbung unterth\u00e4nigst und gehorsamst ein Christian Hartmann, Rector", "creator": "Hartmann, Christian", "spatialClusterName": "C\u00f6then", "spatialClean": "C\u00f6then", "spatialRaw": "C\u00f6then", "mediatype": "Monograph", "subject": "Historische Drucke", "source": "Hartmann, Christian: Den richtigen Begrif der Liebe der Lehrer gegen die Sch\u00fcler zeiget k\u00fcrzlich, und ladet zugleich Hochgeneigte G\u00f6nner und Freunde unserer Evangelisch-Lutherischen Schule zu der auf den 30ten April 1759. \u00f6ffentlich anzustellenden Pr\u00fcfung der Schuliugend und einer damit verbundenen Red\u00fcbung unterth\u00e4nigst und gehorsamst ein Christian Hartmann, Rector. C\u00f6then  Berlin 1759", "publisher": "Sch\u00f6ndorf", "alternative": "nan", "lat": "52.793057", "lng": "13.9355243", "textCluster": "3241", "creatorCluster": "480"}