{"ppn": "PPN73862926X", "dateClean": "1525", "title": "Etliche trostspr\u00fcch || f\u00fcr die forchtsamen v\u00f1 schwa=||chen gewissen/ Gehandelt || durch Doctor Johann\u1ebd || Brie\u00dfman Eccle=||siasten zu K\u0153=||nigsperg in || Preussen || ... ||", "creator": "Briesmann, Johannes", "spatialClusterName": "N\u00fcrnberg", "spatialClean": "N\u00fcrnberg", "spatialRaw": "N\u00fcrnberg", "mediatype": "Monograph", "subject": "Historische Drucke", "source": "Briesmann, Johannes: Etliche trostspr\u00fcch || f\u00fcr die forchtsamen v\u00f1 schwa=||chen gewissen/ Gehandelt || durch Doctor Johann\u1ebd || Brie\u00dfman Eccle=||siasten zu K\u0153=||nigsperg in || Preussen || ... ||. N\u00fcrnberg  Berlin 1525", "publisher": "Gutknecht, Jobst", "alternative": "nan", "lat": "49.4538723", "lng": "11.0772978", "textCluster": "9", "creatorCluster": "8446"}