{"ppn": "PPN796342873", "dateClean": "1840", "title": "Gesetze f\u00fcr die Mitglieder der Loge Friedrich zur Tugend zu Brandenburg in besonderer Beziehung auf ihr gesellschaftliches Verh\u00e4ltni\u00df", "creator": "nan", "spatialClusterName": "Brandenburg", "spatialClean": "Brandenburg", "spatialRaw": "Brandenburg", "mediatype": "Monograph", "subject": "Historische Drucke", "source": "Gesetze f\u00fcr die Mitglieder der Loge Friedrich zur Tugend zu Brandenburg in besonderer Beziehung auf ihr gesellschaftliches Verh\u00e4ltni\u00df  Brandenburg, im M\u00e4rz 1840. Brandenburg  Berlin 1840", "publisher": "Wiesike", "alternative": "Brandenburg, im M\u00e4rz 1840", "lat": "52.8455492", "lng": "13.2461296", "textCluster": "9", "creatorCluster": "0"}