{"spatialClusterName": "Hirschberg", "creator": "Abla\u00df, Bruno  Hauptmann, Gerhart", "spatialRaw": "Hirschberg i/Schl.", "title": "Brief von Bruno Abla\u00df an Gerhart Hauptmann", "publisher": "nan", "mediatype": "Text", "spatialClean": "Hirschberg", "source": "Abla\u00df, Bruno  Hauptmann, Gerhart: Brief von Bruno Abla\u00df an Gerhart Hauptmann. Hirschberg i/Schl.  Berlin", "dateClean": "1738", "lat": "50.9031028", "alternative": "nan", "lng": "15.7344306", "subject": "Nachl\u00e4sse und Autographe"}