{"ppn": "PPN715543210", "dateClean": "1632", "title": "Epicedium. Uber den Hochtraurigen und T\u00f6dtlichen Abschiedt Der ... Anna Magdalena Frawen von Weltz/ Geborner Herrin von Stubenberg [et]c. De\u00df ... Frantzen/ Herren von Weltz ... Gemahlin.", "creator": "Schwopius, Johannes Baptista  Stubenberg, Anna Magdalena", "spatialClusterName": "Stra\u00dfburg", "spatialClean": "Stra\u00dfburg", "spatialRaw": "Stra\u00dfburg", "mediatype": "Monograph", "subject": "Historische Drucke", "source": "Schwopius, Johannes Baptista  Stubenberg, Anna Magdalena: Epicedium. Uber den Hochtraurigen und T\u00f6dtlichen Abschiedt Der ... Anna Magdalena Frawen von Weltz/ Geborner Herrin von Stubenberg [et]c. De\u00df ... Frantzen/ Herren von Weltz ... Gemahlin.  Die Seliglich und Christlich im Herren entschlaffen allhier zu Stra\u00dfburg/ Den 19. Februarii/ Anno M.DC.XXXII.. Stra\u00dfburg  Berlin 1632", "publisher": "Welper", "alternative": "Die Seliglich und Christlich im Herren entschlaffen allhier zu Stra\u00dfburg/ Den 19. Februarii/ Anno M.DC.XXXII.", "lat": "48.584614", "lng": "7.7507127", "textCluster": "9", "creatorCluster": "6"}