{"spatialClusterName": "Leipzig", "creator": "Thieme, Karl Traugott  Dolz, Johann Christian", "spatialRaw": "Leipzig", "title": "Erste Nahrung f\u00fcr den gesunden Menschenverstand", "publisher": "Vogel", "mediatype": "Monograph", "spatialClean": "Leipzig", "source": "Thieme, Karl Traugott  Dolz, Johann Christian: Erste Nahrung f\u00fcr den gesunden Menschenverstand. Leipzig  Berlin", "dateClean": "1738", "lat": "51.3391827", "alternative": "nan", "lng": "12.3810549", "subject": "Kinder und Jugendb\u00fccher"}