{"ppn": "PPN720850924", "dateClean": "1765", "title": "Gegr\u00fcndete Wahrheiten der christlichen Religion", "creator": "Jacobi, Christoph Gottfried", "spatialClusterName": "Magdeburg", "spatialClean": "Magdeburg", "spatialRaw": "Magdeburg", "mediatype": "Monograph", "subject": "Historische Drucke", "source": "Jacobi, Christoph Gottfried: Gegr\u00fcndete Wahrheiten der christlichen Religion. Magdeburg  Berlin 1765", "publisher": "Hechtel", "alternative": "nan", "lat": "52.1315889", "lng": "11.6399609", "textCluster": "9", "creatorCluster": "1315"}