{"ppn": "PPN715184105", "dateClean": "1593", "title": "POSITIONES || PHILOSOPHICAE DE || TOTO ANIMARVM || GENERE.|| Quae in alma & Florenti vniuersitate Herbipolensi disputatae sunt septimo Idus Aprilis || Anni 1593. in aula Philoso-||phorum maiori.|| DEFENDENTE PRO SVPREMA PHILOSOPHIAE LAV-||rea indipiscenda Reuerendo P. Fr. M. Cas-||paro Flaschendrebero Carolstadiano, ex || religiosa Dominicanorum fami-||lia Monasterij Her-||bipolensis.||", "creator": "Flaschendreber, Caspar", "spatialClusterName": "W\u00fcrzburg", "spatialClean": "W\u00fcrzburg", "spatialRaw": "W\u00fcrzburg", "mediatype": "Monograph", "subject": "Historische Drucke", "source": "Flaschendreber, Caspar: POSITIONES || PHILOSOPHICAE DE || TOTO ANIMARVM || GENERE.|| Quae in alma & Florenti vniuersitate Herbipolensi disputatae sunt septimo Idus Aprilis || Anni 1593. in aula Philoso-||phorum maiori.|| DEFENDENTE PRO SVPREMA PHILOSOPHIAE LAV-||rea indipiscenda Reuerendo P. Fr. M. Cas-||paro Flaschendrebero Carolstadiano, ex || religiosa Dominicanorum fami-||lia Monasterij Her-||bipolensis.||. W\u00fcrzburg  Berlin 1593", "publisher": "Fleischmann, Georg", "alternative": "nan", "lat": "49.79245", "lng": "9.932966", "textCluster": "9", "creatorCluster": "1814"}