{"ppn": "PPN776582569", "dateClean": "1789", "title": "Abhandlung das Staatsrecht der Stadt Stra\u00dfburg und des Elsa\u00dfes \u00fcberhaupt betreffend", "creator": "T\u00fcrckheim, Johann", "spatialClusterName": "Stra\u00dfburg", "spatialClean": "Strassburg", "spatialRaw": "Strassburg", "mediatype": "Monograph", "subject": "Historische Drucke", "source": "T\u00fcrckheim, Johann: Abhandlung das Staatsrecht der Stadt Stra\u00dfburg und des Elsa\u00dfes \u00fcberhaupt betreffend  Aus dem Franz\u00f6sischen \u00fcbersetzt. Strassburg  Berlin 1789", "publisher": "Dannbach", "alternative": "Aus dem Franz\u00f6sischen \u00fcbersetzt", "lat": "48.584614", "lng": "7.7507127", "textCluster": "9", "creatorCluster": "6"}