{"ppn": "PPN736422498", "dateClean": "1865", "title": "Allgemeines Berggesetz f\u00fcr die Preu\u00dfischen Staaten", "creator": "nan", "spatialClusterName": "Elberfeld", "spatialClean": "Elberfeld", "spatialRaw": "Elberfeld", "mediatype": "Monograph", "subject": "Rechtswissenschaft", "source": "Allgemeines Berggesetz f\u00fcr die Preu\u00dfischen Staaten  in Kraft vom 1. October 1865. Elberfeld  Berlin 1865", "publisher": "Friderichs", "alternative": "in Kraft vom 1. October 1865", "lat": "51.2573333", "lng": "7.1458183", "textCluster": "3077", "creatorCluster": "0"}