{"ppn": "PPN781109132", "dateClean": "1636", "title": "Nachricht und Information: Wegen der im Namen/ Der K\u00f6niglichen May. und Hochl\u00f6blichen Cron Schweden/ zwischen deroselben Raht ... Herrn Axel Oxenstirn ... Wie auch ... Feldmarschall/ Herrn Johan Banern ... An einem; Und dann ... Herrn Johann Georgen/ Hertzogen zu Sachsen ... Am andern theil; Eine zeithero ver\u00fcbten Acten und Tractaten", "creator": "Oxenstierna, Axel  Ban\u00e9r, Johan", "spatialClusterName": "None", "spatialClean": "", "spatialRaw": "[S.l.]", "mediatype": "Monograph", "subject": "Historische Drucke", "source": "Oxenstierna, Axel  Ban\u00e9r, Johan: Nachricht und Information: Wegen der im Namen/ Der K\u00f6niglichen May. und Hochl\u00f6blichen Cron Schweden/ zwischen deroselben Raht ... Herrn Axel Oxenstirn ... Wie auch ... Feldmarschall/ Herrn Johan Banern ... An einem; Und dann ... Herrn Johann Georgen/ Hertzogen zu Sachsen ... Am andern theil; Eine zeithero ver\u00fcbten Acten und Tractaten. [S.l.]  Berlin 1636", "publisher": "nan", "alternative": "nan", "lat": "nan", "lng": "nan", "textCluster": "9", "creatorCluster": "5140"}