{"spatialClusterName": "Berlin", "creator": "Burmann, Gottlob Wilhelm  Stahlbaum, Christian Ludwig", "spatialRaw": "Berlin", "title": "Kleine Lieder f\u00fcr kleine M\u00e4dchen, und J\u00fcnglinge", "publisher": "Decker", "mediatype": "Monograph", "spatialClean": "Berlin", "source": "Burmann, Gottlob Wilhelm  Stahlbaum, Christian Ludwig: Kleine Lieder f\u00fcr kleine M\u00e4dchen, und J\u00fcnglinge. Berlin  Berlin 1777", "dateClean": "1777", "lat": "52.5170365", "alternative": "nan", "lng": "13.3888599", "subject": "Historische Drucke"}