{"spatialClusterName": "None", "creator": "Moritz < Sachsen, Kurf\u00fcrst>,", "spatialRaw": "s.l.", "title": "Hertzog Moritz Chur||fuerst zu Sachssen Burgraff zu || Magdeburg Lied im thon Ob || ich schon Arm vnd || Elendt Bin.|| etc.||", "publisher": "nan", "mediatype": "Monograph", "spatialClean": "", "source": "Moritz < Sachsen, Kurf\u00fcrst>,: Hertzog Moritz Chur||fuerst zu Sachssen Burgraff zu || Magdeburg Lied im thon Ob || ich schon Arm vnd || Elendt Bin.|| etc.||. s.l.  Berlin 1552", "dateClean": "1552", "lat": "nan", "alternative": "nan", "lng": "nan", "subject": "Historische Drucke"}