{"spatialClusterName": "Paris", "creator": "Scheffer, Karel Arnold", "spatialRaw": "Paris  Paris  Bruxelles  Varsovie", "title": "Tableau Politique De L'Allemagne", "publisher": "Plancher  Delaunay  Lecharlier  Glucksberg", "mediatype": "Monograph", "spatialClean": "Paris", "source": "Scheffer, Karel Arnold: Tableau Politique De L'Allemagne. Paris  Paris  Bruxelles  Varsovie  Berlin 1816", "dateClean": "1816", "lat": "48.8566101", "alternative": "nan", "lng": "2.3514992", "subject": "Historische Drucke"}