{"ppn": "PPN768273404", "dateClean": "1854", "title": "La marguerite", "creator": "Sz\u00e9ch\u00e9nyi, E.", "spatialClusterName": "Mayence", "spatialClean": "Mayence", "spatialRaw": "Mayence [u.a.]", "mediatype": "Monograph", "subject": "Musiknoten", "source": "Sz\u00e9ch\u00e9nyi, E.: La marguerite  Mazurka ; pour le piano. Mayence [u.a.] 1854", "publisher": "Schott [u.a.]", "alternative": "Mazurka ; pour le piano", "lat": "49.9999952", "lng": "8.2710237", "textCluster": "234", "creatorCluster": "966"}