{"ppn": "PPN738218804", "dateClean": "1776", "title": "Poetische Versuche eines adelichen Frauenzimmers an ihre Freunde", "creator": "Titzenhofer, Sophie Eleonore Helene", "spatialClusterName": "Breslau", "spatialClean": "Breslau", "spatialRaw": "Breslau  Leipzig", "mediatype": "Monograph", "subject": "Historische Drucke", "source": "Titzenhofer, Sophie Eleonore Helene: Poetische Versuche eines adelichen Frauenzimmers an ihre Freunde. Breslau  Leipzig  Berlin 1776", "publisher": "Gutsch", "alternative": "nan", "lat": "51.1089776", "lng": "17.0326689", "textCluster": "9", "creatorCluster": "6"}