{"spatialClusterName": "Wien", "creator": "Garcaeus, Johannes", "spatialRaw": "Wittenberg", "title": "Die gar tr\u00f6stliche || sch\u00f6ne Parabel/ von dem getrewen fro=||men Samariter/ vnnd dem verwundten Men=||schen/ beschrieben durch den heiligen Euan=||gelisten Lucam Cap. 10. Gefas=||set in eine einfeltige verma=||nung/|| Durch || Johannem Garcaeum.|| ... ||", "publisher": "nan", "mediatype": "Monograph", "spatialClean": "Wittenberg", "source": "Garcaeus, Johannes: Die gar tr\u00f6stliche || sch\u00f6ne Parabel/ von dem getrewen fro=||men Samariter/ vnnd dem verwundten Men=||schen/ beschrieben durch den heiligen Euan=||gelisten Lucam Cap. 10. Gefas=||set in eine einfeltige verma=||nung/|| Durch || Johannem Garcaeum.|| ... ||. Wittenberg  Berlin 1569", "dateClean": "1569", "lat": "48.2083537", "alternative": "nan", "lng": "16.3725042", "subject": "Historische Drucke"}