{"spatialClusterName": "Frankfurt/Oder", "creator": "Musculus, Andreas", "spatialRaw": "Frankfurt/Oder", "title": "Von || De\u0169tschlandes || bi\u00df in Himmel erh\u00f6hung/|| Nun aber zunahender/ bi\u00df in || die Helle ernidrigung.|| Durch || Andream Musculum D.|| ... ||", "publisher": "Eichorn, Johann", "mediatype": "Monograph", "spatialClean": "Frankfurt/Oder", "source": "Musculus, Andreas: Von || De\u0169tschlandes || bi\u00df in Himmel erh\u00f6hung/|| Nun aber zunahender/ bi\u00df in || die Helle ernidrigung.|| Durch || Andream Musculum D.|| ... ||. Frankfurt/Oder  Berlin 1573", "dateClean": "1573", "lat": "52.3412273", "alternative": "nan", "lng": "14.549452", "subject": "Historische Drucke"}