{"ppn": "PPN737917148", "dateClean": "1665", "title": "Auff die Hochzeit De\u00df Ehrbahren und wolgeachten Herrn Adam Naglo/ B\u00fcrgers und Handelmannes in Creutzberg und Der Viel- Ehren- Tugendreichen Jungfer Dorothea/ De\u00df Ehrenvesten und Wolgelahrten Herrn Johann Stillers/ Wolverordneten Stadt Schreibers in Pitschen/ Eheleiblichen Tochter/ auch des ... Herrn Danielis Schmejen/ Dieser zeit/ der Stadt Pitschen ... Burgemeisters/ Getreuen Pflege Tochter", "creator": "Treyheis, Hans  Naglo, Adam  Naglo, Dorothea  Puklerzsky, Jan", "spatialClusterName": "Oel\u00df", "spatialClean": "Oel\u00df", "spatialRaw": "Oel\u00df", "mediatype": "Monograph", "subject": "Historische Drucke", "source": "Treyheis, Hans  Naglo, Adam  Naglo, Dorothea  Puklerzsky, Jan: Auff die Hochzeit De\u00df Ehrbahren und wolgeachten Herrn Adam Naglo/ B\u00fcrgers und Handelmannes in Creutzberg und Der Viel- Ehren- Tugendreichen Jungfer Dorothea/ De\u00df Ehrenvesten und Wolgelahrten Herrn Johann Stillers/ Wolverordneten Stadt Schreibers in Pitschen/ Eheleiblichen Tochter/ auch des ... Herrn Danielis Schmejen/ Dieser zeit/ der Stadt Pitschen ... Burgemeisters/ Getreuen Pflege Tochter. Oel\u00df  Berlin 1665", "publisher": "Seyffert", "alternative": "nan", "lat": "nan", "lng": "nan", "textCluster": "9", "creatorCluster": "6"}