{"ppn": "PPN756699452", "dateClean": "1646", "title": "Zwey Weltliche Newe Lieder", "creator": "nan", "spatialClusterName": "None", "spatialClean": "", "spatialRaw": "[S.l.]", "mediatype": "Monograph", "subject": "Historische Drucke", "source": "Zwey Weltliche Newe Lieder  Das Erste/ Jetzunder f\u00e4llt die Nacht herein/ Vieh unnd Menschen schlaffen ein. Das Ander. Ach ich armes M\u00e4gdlein/ klage/ das nun meine beste Tage. [S.l.]  Berlin 1646", "publisher": "nan", "alternative": "Das Erste/ Jetzunder f\u00e4llt die Nacht herein/ Vieh unnd Menschen schlaffen ein. Das Ander. Ach ich armes M\u00e4gdlein/ klage/ das nun meine beste Tage", "lat": "nan", "lng": "nan", "textCluster": "493", "creatorCluster": "0"}