{"ppn": "PPN767912470", "dateClean": "1738", "title": "Neuer Orbis pictus f\u00fcr die Jugend", "creator": "Gailer, J. E.  Comenius, ...", "spatialClusterName": "Reutlingen", "spatialClean": "Reutlingen", "spatialRaw": "Reutlingen", "mediatype": "Monograph", "subject": "Kinder und Jugendb\u00fccher", "source": "Gailer, J. E.  Comenius, ...: Neuer Orbis pictus f\u00fcr die Jugend  oder Schauplatz der Natur, der Kunst und des Menschenlebens in 316 lithographirten Abbildungen mit genauer Erkl\u00e4rung in deutscher, lateinischer und franz\u00f6sischer Sprache ; nach der fr\u00fcheren Anlage des Comenius bearbeitet und dem jetzigen Zeitbed\u00fcrfnisse gem\u00e4\u00df eingerichtet. Reutlingen  Berlin", "publisher": "M\u00e4cken", "alternative": "oder Schauplatz der Natur, der Kunst und des Menschenlebens in 316 lithographirten Abbildungen mit genauer Erkl\u00e4rung in deutscher, lateinischer und franz\u00f6sischer Sprache ; nach der fr\u00fcheren Anlage des Comenius bearbeitet und dem jetzigen Zeitbed\u00fcrfnisse gem\u00e4\u00df eingerichtet", "lat": "48.4919508", "lng": "9.2114144", "textCluster": "519", "creatorCluster": "3539"}