{"ppn": "PPN727069268", "dateClean": "1817", "title": "Kurze Geschichte der Reformation zu Biberach, vom Jahr 1517 bis zum Jahr 1650", "creator": "nan", "spatialClusterName": "Ulm", "spatialClean": "Ulm", "spatialRaw": "Ulm", "mediatype": "Monograph", "subject": "Historische Drucke", "source": "Kurze Geschichte der Reformation zu Biberach, vom Jahr 1517 bis zum Jahr 1650  Zur Feier des Jubeljahrs 1817 auf Kosten der evangelischen Schulcasse an die evangelische Schuljugend ausgetheilt. Ulm  Berlin 1817", "publisher": "Ebner", "alternative": "Zur Feier des Jubeljahrs 1817 auf Kosten der evangelischen Schulcasse an die evangelische Schuljugend ausgetheilt", "lat": "48.3973944", "lng": "9.9932755", "textCluster": "9", "creatorCluster": "0"}