{"ppn": "PPN734344341", "dateClean": "1738", "title": "Schriftprobe Kopist J. G. Neidhardt I (Blechschmidt)", "creator": "Kopist J. G. Neidhardt I (Blechschmidt),", "spatialClusterName": "None", "spatialClean": "", "spatialRaw": "nan", "mediatype": "Text", "subject": "Schl\u00fcsselseiten", "source": "Kopist J. G. Neidhardt I (Blechschmidt),: Schriftprobe Kopist J. G. Neidhardt I (Blechschmidt). Berlin", "publisher": "nan", "alternative": "nan", "lat": "nan", "lng": "nan", "textCluster": "2110", "creatorCluster": "2174"}