{"ppn": "PPN780039122", "dateClean": "1565", "title": "Ein newes Lied/|| Von dem Sch\u00fcttensamen/|| vnd seinem falschen Knecht.|| Jm Thon:|| Wie man singt von dem K\u00f6nig von Pa=||ris/ der sein Tochter beschlieff/|| vnd schwanger ward/ #c.||", "creator": "Kugler, Hans", "spatialClusterName": "Augsburg", "spatialClean": "Augsburg", "spatialRaw": "Augsburg", "mediatype": "Monograph", "subject": "Historische Drucke", "source": "Kugler, Hans: Ein newes Lied/|| Von dem Sch\u00fcttensamen/|| vnd seinem falschen Knecht.|| Jm Thon:|| Wie man singt von dem K\u00f6nig von Pa=||ris/ der sein Tochter beschlieff/|| vnd schwanger ward/ #c.||. Augsburg  Berlin 1565", "publisher": "Franck, Matth\u00e4us", "alternative": "nan", "lat": "48.3668041", "lng": "10.8986971", "textCluster": "9", "creatorCluster": "901"}