{"ppn": "PPN797898409", "dateClean": "1534", "title": "Uon der ei=||nigkeyt der kirchen/|| Durch Erasmum von Rote=||rodam/ ytzt new ausgan=||gen.|| ... || [\u00dcbers.v. Georg Witzel d.\u00c4.]", "creator": "Erasmus, Desiderius  Witzel, Georg", "spatialClusterName": "Erfurt", "spatialClean": "Erfurt", "spatialRaw": "Erfurt", "mediatype": "Monograph", "subject": "Historische Drucke", "source": "Erasmus, Desiderius  Witzel, Georg: Uon der ei=||nigkeyt der kirchen/|| Durch Erasmum von Rote=||rodam/ ytzt new ausgan=||gen.|| ... || [\u00dcbers.v. Georg Witzel d.\u00c4.]. Erfurt  Berlin 1534", "publisher": "Maler, Matthes", "alternative": "nan", "lat": "50.9777974", "lng": "11.0287364", "textCluster": "9", "creatorCluster": "3650"}