{"ppn": "PPN718733738", "dateClean": "1896", "title": "Der Preu\u00dfische Gerichtsvollzieher", "creator": "Sch\u00f6nfeld, Hermann", "spatialClusterName": "Breslau", "spatialClean": "Breslau", "spatialRaw": "Breslau", "mediatype": "Monograph", "subject": "Rechtswissenschaft", "source": "Sch\u00f6nfeld, Hermann: Der Preu\u00dfische Gerichtsvollzieher  eine Zusammenstellung und Erl\u00e4uterung s\u00e4mmtlicher f\u00fcr den Dienst der Gerichtsvollzieher ma\u00dfgebenden Bestimmungen ; als Handbuch f\u00fcr die Gerichtsvorst\u00e4nde, Richter und Rechtsanw\u00e4lte, sowie als Lehrbuch f\u00fcr die Gerichtsvollzieher. Breslau  Berlin 1896", "publisher": "Kern", "alternative": "eine Zusammenstellung und Erl\u00e4uterung s\u00e4mmtlicher f\u00fcr den Dienst der Gerichtsvollzieher ma\u00dfgebenden Bestimmungen ; als Handbuch f\u00fcr die Gerichtsvorst\u00e4nde, Richter und Rechtsanw\u00e4lte, sowie als Lehrbuch f\u00fcr die Gerichtsvollzieher", "lat": "51.1089776", "lng": "17.0326689", "textCluster": "1135", "creatorCluster": "4276"}