{"ppn": "PPN779186729", "dateClean": "1755", "title": "Geschichte Sir Heinrich Heralds und Sir Eduard Haunchs", "creator": "nan", "spatialClusterName": "Leipzig", "spatialClean": "Leipzig", "spatialRaw": "Leipzig", "mediatype": "Monograph", "subject": "Historische Drucke", "source": "Geschichte Sir Heinrich Heralds und Sir Eduard Haunchs  In drey Theilen aus dem Englischen \u00fcbersetzt. Leipzig  Berlin 1755", "publisher": "Wendler", "alternative": "In drey Theilen aus dem Englischen \u00fcbersetzt", "lat": "51.3391827", "lng": "12.3810549", "textCluster": "9", "creatorCluster": "0"}