{"ppn": "PPN799201820", "dateClean": "1786", "title": "Die F\u00fcnfte.", "creator": "nan", "spatialClusterName": "None", "spatialClean": "", "spatialRaw": "[S.l.]", "mediatype": "Other", "subject": "Historische Drucke", "source": "Die F\u00fcnfte.  Lieschens Antwort aus der Fremde, an dem lieben Augustin. Nach der Melodie: Sagt wo sind die Veilchen hin.. [S.l.]  Berlin 1786", "publisher": "nan", "alternative": "Lieschens Antwort aus der Fremde, an dem lieben Augustin. Nach der Melodie: Sagt wo sind die Veilchen hin.", "lat": "nan", "lng": "nan", "textCluster": "48", "creatorCluster": "0"}