{"ppn": "PPN771166850", "dateClean": "1738", "title": "Brief von Rudolf G. Binding, Elisabeth Beerbohm und Anton Kippenberg an Gerhart Hauptmann", "creator": "Binding, Rudolf G.  Beerbohm, Elisabeth  Kippenberg, Anton  Hauptmann, Gerhart", "spatialClusterName": "Buchschlag", "spatialClean": "Buchschlag", "spatialRaw": "Buchschlag", "mediatype": "Text", "subject": "Nachl\u00e4sse und Autographe", "source": "Binding, Rudolf G.  Beerbohm, Elisabeth  Kippenberg, Anton  Hauptmann, Gerhart: Brief von Rudolf G. Binding, Elisabeth Beerbohm und Anton Kippenberg an Gerhart Hauptmann. Buchschlag  Berlin", "publisher": "nan", "alternative": "nan", "lat": "49.869478", "lng": "9.5551855", "textCluster": "935", "creatorCluster": "211"}