{"spatialClusterName": "Emden", "creator": "Hantelmann, Ernst", "spatialRaw": "Emden", "title": "Bekanntmachung. Das nach unserer Bekanntmachung vom 15. Oktober 1856 einstweilen auf 2 resv. 3 Pfenn. in alter M\u00fcnze f\u00fcr dem Centner festgesetzte L\u00f6schgeld f\u00fcr die Benutzung des st\u00e4dtischen Krans in der zollamtlichen L\u00f6schhalle ...", "publisher": "Hahn", "mediatype": "Monograph", "spatialClean": "Emden", "source": "Hantelmann, Ernst: Bekanntmachung. Das nach unserer Bekanntmachung vom 15. Oktober 1856 einstweilen auf 2 resv. 3 Pfenn. in alter M\u00fcnze f\u00fcr dem Centner festgesetzte L\u00f6schgeld f\u00fcr die Benutzung des st\u00e4dtischen Krans in der zollamtlichen L\u00f6schhalle ...  Emden, den 6. Oktober 1858. Emden  Berlin 1858", "dateClean": "1858", "lat": "53.3670442", "alternative": "Emden, den 6. Oktober 1858", "lng": "7.2058004", "subject": "Rechtswissenschaft"}