{"ppn": "PPN771820852", "dateClean": "1738", "title": "Brief von Hermann Haussmann und Hildegard Haussmann an Gerhart Hauptmann und Margarete Hauptmann", "creator": "Haussmann, Hermann  Haussmann, Hildegard  Hauptmann, Gerhart  Hauptmann, Margarete", "spatialClusterName": "Emmendingen", "spatialClean": "Emmendingen", "spatialRaw": "Emmendingen [Poststempel]", "mediatype": "Text", "subject": "Nachl\u00e4sse und Autographe", "source": "Haussmann, Hermann  Haussmann, Hildegard  Hauptmann, Gerhart  Hauptmann, Margarete: Brief von Hermann Haussmann und Hildegard Haussmann an Gerhart Hauptmann und Margarete Hauptmann. Emmendingen [Poststempel]  Berlin", "publisher": "nan", "alternative": "nan", "lat": "48.1206565", "lng": "7.850993", "textCluster": "1416", "creatorCluster": "9737"}