{"ppn": "PPN78055258X", "dateClean": "1596", "title": "Leichpredig || BEy dem Begrebnus || des Ehrw\u00fcrdigen/ Achtbarn vnnd Wolge=||larten Herrn/ M. HIERONYMI NYM-||MANI Archidiaconi zu Torgaw/ gethan || den 20. Nouembris/ Anno || 1592.|| Von || TOBIA BEVTHERN,|| Pfarrherrn vnd Superintendenten || daselbsten.||", "creator": "Beuther, Tobias  Nymann, Hieronymus", "spatialClusterName": "Wittenberg", "spatialClean": "Wittenberg", "spatialRaw": "Wittenberg", "mediatype": "Monograph", "subject": "Historische Drucke", "source": "Beuther, Tobias  Nymann, Hieronymus: Leichpredig || BEy dem Begrebnus || des Ehrw\u00fcrdigen/ Achtbarn vnnd Wolge=||larten Herrn/ M. HIERONYMI NYM-||MANI Archidiaconi zu Torgaw/ gethan || den 20. Nouembris/ Anno || 1592.|| Von || TOBIA BEVTHERN,|| Pfarrherrn vnd Superintendenten || daselbsten.||. Wittenberg  Berlin 1596", "publisher": "Meissner, Wolfgang", "alternative": "nan", "lat": "51.91552465", "lng": "12.6427281489121", "textCluster": "9", "creatorCluster": "4703"}