{"ppn": "PPN771809506", "dateClean": "1738", "title": "Brief von Annelise Herrmann und Wolfgang Herrmann an Gerhart Hauptmann", "creator": "Herrmann, Annelise  Hauptmann, Gerhart", "spatialClusterName": "Berlin", "spatialClean": "Berlin", "spatialRaw": "Berlin", "mediatype": "Text", "subject": "Nachl\u00e4sse und Autographe", "source": "Herrmann, Annelise  Hauptmann, Gerhart: Brief von Annelise Herrmann und Wolfgang Herrmann an Gerhart Hauptmann. Berlin  Berlin", "publisher": "nan", "alternative": "nan", "lat": "52.5170365", "lng": "13.3888599", "textCluster": "664", "creatorCluster": "1033"}