{"ppn": "PPN751123994", "dateClean": "1855", "title": "Das B\u00fcreau-Reglement vom 3. August 1841 mit den bis auf die neueste Zeit ergangenen Erg\u00e4nzungen und Erl\u00e4uterungen", "creator": "Liebgott, L.", "spatialClusterName": "Schmiedeberg", "spatialClean": "Sch\u00f6nebeck", "spatialRaw": "Sch\u00f6nebeck", "mediatype": "Monograph", "subject": "Rechtswissenschaft", "source": "Liebgott, L.: Das B\u00fcreau-Reglement vom 3. August 1841 mit den bis auf die neueste Zeit ergangenen Erg\u00e4nzungen und Erl\u00e4uterungen. Sch\u00f6nebeck  Berlin 1855", "publisher": "Berger", "alternative": "nan", "lat": "50.8349379", "lng": "13.6794256", "textCluster": "9", "creatorCluster": "1364"}