{"spatialClusterName": "G\u00fcstrow", "creator": "Alard, Christian", "spatialRaw": "G\u00fcstrow", "title": "Malchinsches Denckmahl nach abgelegten Evangelisch-Lutherschen Jubel-Fest", "publisher": "Lembke", "mediatype": "Monograph", "spatialClean": "G\u00fcstrow", "source": "Alard, Christian: Malchinsches Denckmahl nach abgelegten Evangelisch-Lutherschen Jubel-Fest  welches auff Hoch-F\u00fcrstl. Verordnung den 31 Octobr. und 1 Novembr. des 1717. Jahrs in Malchin Christ-billich gefeyret worden, in einigen Fragen und Antworten Von der Reformation. G\u00fcstrow  Berlin 1717", "dateClean": "1717", "lat": "53.7936523", "alternative": "welches auff Hoch-F\u00fcrstl. Verordnung den 31 Octobr. und 1 Novembr. des 1717. Jahrs in Malchin Christ-billich gefeyret worden, in einigen Fragen und Antworten Von der Reformation", "lng": "12.1759661", "subject": "Historische Drucke"}