{"spatialClusterName": "Helmstedt", "creator": "Hardt, Hermannus von der", "spatialRaw": "Helmaestadii", "title": "Decertare. Festo Michaelis In Academia Jvlia In Literatorvm Civivm Emolvmentvm, A. MDCCXXIX. D. XXIX. Sept. P. P", "publisher": "Schnorrius", "mediatype": "Monograph", "spatialClean": "Helmaestadii", "source": "Hardt, Hermannus von der: Decertare. Festo Michaelis In Academia Jvlia In Literatorvm Civivm Emolvmentvm, A. MDCCXXIX. D. XXIX. Sept. P. P. Helmaestadii  Berlin 1729", "dateClean": "1729", "lat": "52.2277037", "alternative": "nan", "lng": "11.0104702", "subject": "Historische Drucke"}