{"ppn": "PPN812881125", "dateClean": "1559", "title": "Der XXXVII || Psalm/ in G\u00f6ttliche vnd || Christliche Fragen gebracht/ sehr tr\u00f6st=||lich/ den armen fromen Christen/ die in der || Welt viel m\u00fcssen leiden/ vnd erschreck=||lich den Gottlosen Tyrannen/ die || in der Welt viel gl\u00fcck vnd || ehr haben/ Also || bereitet || Durch Wolff B\u00fcttner/|| Pfarrherrn zu Ompfferstedt.||", "creator": "B\u00fcttner, Wolfgang  Luther, Martin", "spatialClusterName": "Erfurt", "spatialClean": "Erfurt", "spatialRaw": "Erfurt", "mediatype": "Monograph", "subject": "Historische Drucke", "source": "B\u00fcttner, Wolfgang  Luther, Martin: Der XXXVII || Psalm/ in G\u00f6ttliche vnd || Christliche Fragen gebracht/ sehr tr\u00f6st=||lich/ den armen fromen Christen/ die in der || Welt viel m\u00fcssen leiden/ vnd erschreck=||lich den Gottlosen Tyrannen/ die || in der Welt viel gl\u00fcck vnd || ehr haben/ Also || bereitet || Durch Wolff B\u00fcttner/|| Pfarrherrn zu Ompfferstedt.||. Erfurt  Berlin 1559", "publisher": "Dolgen, Merten von", "alternative": "nan", "lat": "50.9777974", "lng": "11.0287364", "textCluster": "9", "creatorCluster": "32"}