{"ppn": "PPN846050390", "dateClean": "1525", "title": "Diss sind die Zehen gebott: wie sy Gott von wort z\u016f wort|| Moysi vff dem berg Synai anggeben/ vnd mit sinem finger jn zwo steinine taflen geschriben hat.||", "creator": "nan", "spatialClusterName": "Z\u00fcrich", "spatialClean": "Z\u00fcrich", "spatialRaw": "Z\u00fcrich", "mediatype": "Monograph", "subject": "Einblattdrucke", "source": "Diss sind die Zehen gebott: wie sy Gott von wort z\u016f wort|| Moysi vff dem berg Synai anggeben/ vnd mit sinem finger jn zwo steinine taflen geschriben hat.||. Z\u00fcrich  Berlin 1525", "publisher": "Froschauer", "alternative": "nan", "lat": "47.3685586", "lng": "8.5404434", "textCluster": "9", "creatorCluster": "0"}