{"ppn": "PPN815888821", "dateClean": "1890", "title": "Von Bismarck, 1. May 1890", "creator": "Lenbach, Franz  Bismarck, Otto von", "spatialClusterName": "None", "spatialClean": "", "spatialRaw": "nan", "mediatype": "Monograph", "subject": "Einblattdrucke", "source": "Lenbach, Franz  Bismarck, Otto von: Von Bismarck, 1. May 1890  Franz v. Lenbach pinx. Gravure Hanfstaengl. Berlin 1890", "publisher": "nan", "alternative": "Franz v. Lenbach pinx. Gravure Hanfstaengl", "lat": "nan", "lng": "nan", "textCluster": "2558", "creatorCluster": "2945"}