{"spatialClusterName": "Minden", "creator": "Steinow, Rudolph  Schmidt, Gesa", "spatialRaw": "Minden", "title": "Jerm: Thren: 3. Der Augen Thr\u00e4nen-Quell/ und Des Jammer-lechzenden Wassers kl\u00e4gliche Gen\u00fcge", "publisher": "Piler", "mediatype": "Monograph", "spatialClean": "Minden", "source": "Steinow, Rudolph  Schmidt, Gesa: Jerm: Thren: 3. Der Augen Thr\u00e4nen-Quell/ und Des Jammer-lechzenden Wassers kl\u00e4gliche Gen\u00fcge  Uber den himlisch-sehnenden und Wolseeligen Abschied Der ... Frauen Gesimunden gebohrnen Sarnighausen/ Des ... Herrn M. Iulii Schmidts/ Der Chur-Brandenb. Mindischen Pfr\u00fcnde ... Superattendenten, ConsistorialRaht und \u00e4lter Prediger zu Petershagen ... Hau\u00df-Ehe und Ehren Schatzes/ Da dieselbe im Jahr 1675. den 19. Novembr. diese Welt Christ-seeligst gesegnet ... da deren entsehlter K\u00f6rper ... in ihre Erbbegr\u00e4bni\u00df den 29. Nov. zu Petershagen eingesenket worden. Minden  Berlin 1675", "dateClean": "1675", "lat": "52.2881045", "alternative": "Uber den himlisch-sehnenden und Wolseeligen Abschied Der ... Frauen Gesimunden gebohrnen Sarnighausen/ Des ... Herrn M. Iulii Schmidts/ Der Chur-Brandenb. Mindischen Pfr\u00fcnde ... Superattendenten, ConsistorialRaht und \u00e4lter Prediger zu Petershagen ... Hau\u00df-Ehe und Ehren Schatzes/ Da dieselbe im Jahr 1675. den 19. Novembr. diese Welt Christ-seeligst gesegnet ... da deren entsehlter K\u00f6rper ... in ihre Erbbegr\u00e4bni\u00df den 29. Nov. zu Petershagen eingesenket worden", "lng": "8.9168852", "subject": "Historische Drucke"}