{"ppn": "PPN829062505", "dateClean": "1738", "title": "Vorlesungsbericht zur \"Untersuchung der atmosph\u00e4rischen Luft auf organisch geformte Stoffe mittels Leitung derselben durch destiliertes Wasser\"", "creator": "Ehrenberg, Christian Gottfried", "spatialClusterName": "None", "spatialClean": "", "spatialRaw": "nan", "mediatype": "Text", "subject": "Alexander von Humboldt", "source": "Ehrenberg, Christian Gottfried: Vorlesungsbericht zur \"Untersuchung der atmosph\u00e4rischen Luft auf organisch geformte Stoffe mittels Leitung derselben durch destiliertes Wasser\". Berlin", "publisher": "nan", "alternative": "nan", "lat": "nan", "lng": "nan", "textCluster": "3496", "creatorCluster": "3464"}